active_learner/Phrases.py
active_learner/__init__.py
active_learner/al_autophrase.py
active_learner/lsh_analyzer.py
active_learner/lsh_autophrase.py
active_learner/lsh_example_file.py
active_learner/pos_analyzer.py
lsh_example/Phrases.py
lsh_example/__init__.py
lsh_example/al_autophrase.py
lsh_example/lsh_analyzer.py
lsh_example/lsh_autophrase.py
lsh_example/lsh_example_file.py
lsh_example/pos_analyzer.py
active_learner-1.1.0.dist-info/LICENSE
active_learner-1.1.0.dist-info/METADATA
active_learner-1.1.0.dist-info/WHEEL
active_learner-1.1.0.dist-info/top_level.txt
active_learner-1.1.0.dist-info/RECORD
